MANIFEST.in
crm_lead_mc_demo_report.rml
marketing_campaign_demo.xml
setup.py
./__init__.py
./__openerp__.py
i18n/ar.po
i18n/bg.po
i18n/ca.po
i18n/da.po
i18n/de.po
i18n/es.po
i18n/es_CR.po
i18n/es_MX.po
i18n/es_VE.po
i18n/fr.po
i18n/gl.po
i18n/hr.po
i18n/hu.po
i18n/it.po
i18n/ja.po
i18n/marketing_campaign_crm_demo.pot
i18n/mk.po
i18n/nb.po
i18n/nl.po
i18n/pt.po
i18n/pt_BR.po
i18n/ro.po
i18n/ru.po
i18n/sl.po
i18n/sr.po
i18n/sr@latin.po
i18n/tr.po
i18n/zh_CN.po
images/campaigns.jpeg
images/email_templates.jpeg
openerp_marketing_campaign_crm_demo.egg-info/PKG-INFO
openerp_marketing_campaign_crm_demo.egg-info/SOURCES.txt
openerp_marketing_campaign_crm_demo.egg-info/dependency_links.txt
openerp_marketing_campaign_crm_demo.egg-info/requires.txt
openerp_marketing_campaign_crm_demo.egg-info/top_level.txt